rfcpy/__init__.py
rfcpy/helpers/__init__.py
rfcpy/helpers/config.py
rfcpy/helpers/display.py
rfcpy/helpers/utils.py
rfcpy/models.py
rfcpy/rfc.py
rfc.py-2020.10.1.dist-info/entry_points.txt
rfc.py-2020.10.1.dist-info/LICENSE.txt
rfc.py-2020.10.1.dist-info/WHEEL
rfc.py-2020.10.1.dist-info/METADATA
rfc.py-2020.10.1.dist-info/RECORD
